perry_cdom_api_community/__init__.py
perry_cdom_api_community/api.py
perry_cdom_api_community/const.py
perry_cdom_api_community/entity.py
perry_cdom_api_community/http_request.py
perry_cdom_api_community/thermostat.py
perry_cdom_api_community-0.1.2.dist-info/LICENSE
perry_cdom_api_community-0.1.2.dist-info/METADATA
perry_cdom_api_community-0.1.2.dist-info/WHEEL
perry_cdom_api_community-0.1.2.dist-info/RECORD
