Metadata-Version: 2.1
Name: perry_cdom_api_community
Version: 0.1.2
Summary: This is a Python client for the Perry Electric CDOM/CRM4.0 API.
Home-page: https://github.com/ivancoppa/perry_cdom_api_community
Author: Ivan Coppa
Author-email: ivan.coppa@gmail.com
Requires-Python: >=3.10
Classifier: Programming Language :: Python :: 3
Classifier: Programming Language :: Python :: 3.10
Classifier: Programming Language :: Python :: 3.11
Classifier: Programming Language :: Python :: 3.12
Classifier: Programming Language :: Python :: 3.13
Provides-Extra: cli
Requires-Dist: aiohttp (>=3.9.5,<4.0.0)
Requires-Dist: pyjwt (>=2.8.0,<3.0.0)
Project-URL: Repository, https://github.com/ivancoppa/perry_cdom_api_community
